flask_serialize/__init__.py
flask_serialize/flask_serialize.py
flask_serialize/form_page.py
flask_serialize-2.1.3.dist-info/LICENSE
flask_serialize-2.1.3.dist-info/METADATA
flask_serialize-2.1.3.dist-info/WHEEL
flask_serialize-2.1.3.dist-info/top_level.txt
flask_serialize-2.1.3.dist-info/RECORD
