Metadata-Version: 2.1
Name: flask-serialize
Version: 2.1.3
Summary: Easy to use JSON serialization and update/create for Flask and SQLAlchemy.
Home-page: https://github.com/Martlark/flask-serialize
Download-URL: https://github.com/Martlark/flask-serialize/archive/2.1.3.tar.gz
Author: Andrew Rowe
Author-email: rowe.andrew.d@gmail.com
License: Apache Software License
Keywords: flask sqlalchemy serialize serialization serialise
Classifier: Development Status :: 5 - Production/Stable
Classifier: Intended Audience :: Developers
Classifier: Topic :: Software Development :: Libraries :: Python Modules
Classifier: Framework :: Flask
Classifier: License :: OSI Approved :: Apache Software License
Classifier: Programming Language :: Python
Classifier: Programming Language :: Python :: 3
Classifier: Programming Language :: Python :: 3.7
Classifier: Programming Language :: Python :: 3.8
Classifier: Programming Language :: Python :: 3.9
Classifier: Programming Language :: Python :: 3.10
Classifier: Programming Language :: Python :: 3.11
Classifier: Operating System :: POSIX
Classifier: Operating System :: MacOS
Classifier: Operating System :: Unix
Classifier: Operating System :: Microsoft :: Windows
License-File: LICENSE
